Metadata-Version: 2.1
Name: odoo12-addon-website-oca-integrator
Version: 12.0.1.1.0
Summary: Displays Integrators in website.
Home-page: https://github.com/OCA/oca-custom
Author: Odoo Community Association (OCA), Surekha Technologies
Author-email: support@odoo-community.org
License: AGPL-3
Platform: UNKNOWN
Classifier: Programming Language :: Python
Classifier: Framework :: Odoo
Classifier: License :: OSI Approved :: GNU Affero General Public License v3
Requires-Python: >=3.5
Requires-Dist: odoo12-addon-apps-product-creator
Requires-Dist: odoo (<12.1dev,>=12.0a)
